LICENSE
README.md
pyproject.toml
setup.py
Piraha.egg-info/PKG-INFO
Piraha.egg-info/SOURCES.txt
Piraha.egg-info/dependency_links.txt
Piraha.egg-info/top_level.txt
piraha/__init__.py
piraha/colored.py
piraha/here.py
piraha/py.typed
piraha/version.py