Metadata-Version: 2.1
Name: Piraha
Version: 1.1.7
Summary: Parsing Expression Grammar for Python
Home-page: https://github.com/stevenrbrandt/piraha-peg.git
Author: Steven R. Brandt
Author-email: steven@stevenrbrandt.com
License: LGPL
Platform: UNKNOWN
License-File: LICENSE
